tree_guardian/__init__.py
tree_guardian/constants.py
tree_guardian/handle.py
tree_guardian/hash_observer.py
tree_guardian/utils.py
tree_guardian-0.1.3.dist-info/LICENSE
tree_guardian-0.1.3.dist-info/METADATA
tree_guardian-0.1.3.dist-info/WHEEL
tree_guardian-0.1.3.dist-info/top_level.txt
tree_guardian-0.1.3.dist-info/RECORD
