Metadata-Version: 2.1
Name: tree-guardian
Version: 0.1.3
Summary: Track the changes into the filesystem and trigger callback on changes detecting.
Home-page: https://github.com/fadich/tree-guardian
Author: Fadi A.
Author-email: royalfadich@gmail.com
License: UNKNOWN
Platform: UNKNOWN
